odoo/addons/web_responsive/README.rst
odoo/addons/web_responsive/__init__.py
odoo/addons/web_responsive/__manifest__.py
odoo/addons/web_responsive/i18n/ar.po
odoo/addons/web_responsive/i18n/ca.po
odoo/addons/web_responsive/i18n/da.po
odoo/addons/web_responsive/i18n/de.po
odoo/addons/web_responsive/i18n/es.po
odoo/addons/web_responsive/i18n/fa.po
odoo/addons/web_responsive/i18n/fa_IR.po
odoo/addons/web_responsive/i18n/fr.po
odoo/addons/web_responsive/i18n/fr_FR.po
odoo/addons/web_responsive/i18n/hr.po
odoo/addons/web_responsive/i18n/it.po
odoo/addons/web_responsive/i18n/nl.po
odoo/addons/web_responsive/i18n/pt.po
odoo/addons/web_responsive/i18n/pt_BR.po
odoo/addons/web_responsive/i18n/ru.po
odoo/addons/web_responsive/i18n/web_responsive.pot
odoo/addons/web_responsive/i18n/zh_CN.po
odoo/addons/web_responsive/models/__init__.py
odoo/addons/web_responsive/models/res_users.py
odoo/addons/web_responsive/readme/CONTRIBUTORS.rst
odoo/addons/web_responsive/readme/DESCRIPTION.rst
odoo/addons/web_responsive/readme/ROADMAP.rst
odoo/addons/web_responsive/readme/USAGE.rst
odoo/addons/web_responsive/static/description/icon.png
odoo/addons/web_responsive/static/description/index.html
odoo/addons/web_responsive/static/img/appmenu.gif
odoo/addons/web_responsive/static/img/big_checkboxes.gif
odoo/addons/web_responsive/static/img/chatter.gif
odoo/addons/web_responsive/static/img/chatter_topbar.gif
odoo/addons/web_responsive/static/img/document_viewer.gif
odoo/addons/web_responsive/static/img/dropdown_scroll.gif
odoo/addons/web_responsive/static/img/formview.gif
odoo/addons/web_responsive/static/img/label_size_large.png
odoo/addons/web_responsive/static/img/label_size_small.png
odoo/addons/web_responsive/static/img/listview.gif
odoo/addons/web_responsive/static/img/search_panel.gif
odoo/addons/web_responsive/static/src/img/home-menu-bg-overlay.svg
odoo/addons/web_responsive/static/src/js/kanban_renderer_mobile.js
odoo/addons/web_responsive/static/src/js/web_responsive.js
odoo14_addon_web_responsive-14.0.1.2.2.dist-info/METADATA
odoo14_addon_web_responsive-14.0.1.2.2.dist-info/WHEEL
odoo14_addon_web_responsive-14.0.1.2.2.dist-info/top_level.txt
odoo14_addon_web_responsive-14.0.1.2.2.dist-info/RECORD
